auxlibx/__init__.py
auxlibx/np_utils.py
auxlibx/pd_utils.py
auxlibx/plot_utils.py
tests/__init__.py
tests/test_lib.py
auxlibx-0.0.1.dist-info/LICENSE
auxlibx-0.0.1.dist-info/METADATA
auxlibx-0.0.1.dist-info/WHEEL
auxlibx-0.0.1.dist-info/top_level.txt
auxlibx-0.0.1.dist-info/RECORD
